{
    "input": {
        "timestamp": "2023-02-27 05: 14: 00.580892",
        "cpu_percent-0": 2.4,
        "cpu_percent-1": 2.6,
        "cpu_percent-2": 3.4,
        "cpu_percent-3": 1.4,
        "cpu_percent-4": 1.2,
        "cpu_percent-5": 1.8,
        "cpu_percent-6": 2.0,
        "cpu_percent-7": 1.0,
        "cpu_percent-8": 1.2,
        "cpu_percent-9": 2.2,
        "cpu_percent-10": 2.8,
        "cpu_percent-11": 2.2,
        "cpu_percent-12": 1.6,
        "cpu_percent-13": 1.0,
        "cpu_percent-14": 1.4,
        "cpu_percent-15": 1.2,
        "cpu_freq_current": 2999.998999999999,
        "cpu_stats-ctx_switches": 5904018878,
        "cpu_stats-interrupts": 3623555859,
        "cpu_stats-soft_interrupts": 1110167674,
        "cpu_stats-syscalls": 0,
        "virtual_memory-total": 24972115968,
        "virtual_memory-available": 15127023616,
        "virtual_memory-percent": 39.4,
        "virtual_memory-used": 9416937472,
        "virtual_memory-free": 541474816,
        "virtual_memory-active": 5499924480,
        "virtual_memory-inactive": 15699914752,
        "virtual_memory-buffers": 3354624,
        "virtual_memory-cached": 15010349056,
        "virtual_memory-shared": 10227712,
        "virtual_memory-slab": 2201317376,
        "n_pids": 549,
        "net_io_counters_eth0-bytes_sent": 6372734463,
        "net_io_counters_eth0-bytes_recv": 13480058741,
        "net_io_counters_eth0-packets_sent": 4238307,
        "net_io_counters_eth0-packets_recv": 39680485,
        "net_io_counters_eth0-errin": 0,
        "net_io_counters_eth0-errout": 0,
        "net_io_counters_eth0-dropin": 36842,
        "net_io_counters_eth0-dropout": 0
    },
    "context": [
        "confirm_execution",
        "env",
        "function_getmtime",
        "help",
        "host",
        "input_key",
        "last_execution",
        "output_key",
        "port",
        "set_env"
    ]
}